rdf_graph_gen/__init__.py
rdf_graph_gen/multiprocess_generate.py
rdf_graph_gen/rdf_graph_generator.py
rdf_graph_gen/script.py
rdf_graph_gen/shacl_mapping_generator.py
rdf_graph_gen/value_generators.py
rdf_graph_gen/datasets/book_awards.csv
rdf_graph_gen/datasets/book_genre.csv
rdf_graph_gen/datasets/book_titles.csv
rdf_graph_gen/datasets/female_first_name.csv
rdf_graph_gen/datasets/job_title.csv
rdf_graph_gen/datasets/male_first_name.csv
rdf_graph_gen/datasets/movie_awards.csv
rdf_graph_gen/datasets/movie_genre.csv
rdf_graph_gen/datasets/movie_titles.csv
rdf_graph_gen/datasets/street_name.csv
rdf_graph_gen/datasets/surnames.csv
rdf_graph_gen/datasets/tvseries_titles.csv
rdf_graph_gen-1.2.0.dist-info/LICENSE
rdf_graph_gen-1.2.0.dist-info/METADATA
rdf_graph_gen-1.2.0.dist-info/WHEEL
rdf_graph_gen-1.2.0.dist-info/entry_points.txt
rdf_graph_gen-1.2.0.dist-info/top_level.txt
rdf_graph_gen-1.2.0.dist-info/RECORD
