Metadata-Version: 2.1
Name: rdf-graph-gen
Version: 1.2.0
Summary: Synthetic RDF graph generator based on SHACL shapes.
Home-page: UNKNOWN
License: UNKNOWN
Platform: UNKNOWN
Requires-Dist: rdflib>=7.0.0
Requires-Dist: python-dateutil>=2.8.2
Requires-Dist: exrex>=0.11.0
Requires-Dist: setuptools>=69.1.1
